Metadata-Version: 1.0
Name: GBTestdistributions
Version: 0.2
Summary: Gaussian&Binomial distributions
Home-page: UNKNOWN
Author: UNKNOWN
Author-email: UNKNOWN
License: UNKNOWN
Platform: UNKNOWN
